{"id": 36815, "titulo": "Petici\u00f3n de 66 diputados y diputadas quienes, de conformidad con lo dispuesto en el art\u00edculo 52, N\u00b0 1, letra c) de la Constituci\u00f3n Pol\u00edtica de la Rep\u00fablica, y en el art\u00edculo 313 del Reglamento de la Corporaci\u00f3n, solicitan la creaci\u00f3n de una Comisi\u00f3n Especial Investigadora encargada de recabar informaci\u00f3n sobre la administraci\u00f3n y estados financieros de la Empresa Nacional de Miner\u00eda (ENAMI) para determinar eventuales adulteraciones de informaci\u00f3n e irregularidades en su gesti\u00f3n durante los \u00faltimos cinco a\u00f1os, como asimismo, fiscalizar los actos de los \u00f3rganos competentes de la Administraci\u00f3n del Estado relacionados con su funcionamiento en el mismo periodo.", "subtitulo": "", "fecha": [2021, 9, 1, 0, 0, 0, 2, 244, -1], "tipo": "Otros", "resultado": "Aprobado", "quorum": "", "nquorum": -1, "info_por_partido": [{"A favor": {"UDI": 18, "EVOP": 5, "PS": 15, "DC": 9, "IND": 18, "PC": 8, "RN": 25, "PL": 2, "RD": 6, "PPD": 7, "PEV": 1, "PR": 4, "PH": 1, "CO": 2, "FRVS": 3, "PLR": 1, "CS": 3}, "Abstienen": {"UDI": 1, "RN": 2}, "En contra": {"RN": 3}}, {"Ausentes": {"UDI": 6, "RN": 2, "PS": 1, "DC": 2, "PC": 1, "IND": 1}}, [["RN", "PS"], ["UDI", "IND"], ["EVOP", "CS"], ["DC", "RN"]]], "info_por_coalicion": [{"A favor": {"CV": 53, "UC": 42, "SC": 8, "AD": 25}, "Abstienen": {"CV": 3}, "En contra": {"CV": 3}}, {"Ausentes": {"CV": 8, "UC": 3, "AD": 1, "SC": 1}}, [["CV", "UC"], ["CV", "UC"], ["CV", "AD"], ["UC", "CV"]]]}