{"id": 36922, "titulo": "Solicita a S. E. el Presidente de la Rep\u00fablica que env\u00ede un proyecto de ley que  extinga las deudas de los usuarios acogidos a las leyes Nos. 21.249 y 21.340 que regulan el corte de servicios b\u00e1sicos domiciliarios durante la pandemia.", "subtitulo": "", "fecha": [2021, 9, 9, 0, 0, 0, 3, 252, -1], "tipo": "Proyecto Resolucion", "resultado": "Aprobado", "quorum": "", "nquorum": -1, "info_por_partido": [{"A favor": {"IND": 15, "EVOP": 1, "PS": 10, "UDI": 6, "DC": 10, "RD": 5, "PC": 6, "RN": 21, "PPD": 6, "PEV": 1, "PR": 4, "PH": 1, "PL": 1, "CO": 2, "FRVS": 2, "CS": 3}, "Abstienen": {"UDI": 8, "RN": 5, "EVOP": 4}, "En contra": {}}, {"Ausentes": {"UDI": 8, "PL": 1, "IND": 2, "RN": 4, "PS": 4, "PC": 1, "RD": 1, "CS": 1}}, [["RN", "PC"], ["RN", "PC"], ["UDI", "PPD"], ["FRVS", "EVOP"], ["UDI", "PS"], ["DC", "RN"], ["RN", "PS"], ["PLR", "IND"], ["IND", "DC"], ["UDI", "IND"], ["PS", "UDI"]]], "info_por_coalicion": [{"A favor": {"UC": 36, "CV": 31, "AD": 21, "SC": 6}, "Abstienen": {"CV": 17}, "En contra": {}}, {"Ausentes": {"CV": 12, "UC": 5, "SC": 2, "AD": 3}}, [["CV", "AD"], ["CV", "AD"], ["CV", "UC"], ["AD", "CV"], ["CV", "UC"], ["UC", "CV"], ["CV", "UC"], ["CV", "SC"], ["CV", "UC"], ["CV", "UC"], ["UC", "CV"]]]}